[
    {
        "indent": 0,
        "user": "SiliconValleyGuru",
        "text": "I knew it! I always suspected that half of my remote coworkers were too good to be true.",
        "posted": "2023-04-10 16:40:30.379508"
    },
    {
        "indent": 1,
        "user": "JustAnotherCoder",
        "text": "Only half? Your team must have a high concentration of human talent then.",
        "posted": "2023-04-10 16:49:30.379508"
    },
    {
        "indent": 2,
        "user": "QuantumThinker",
        "text": "Or maybe the AI chatbots are just getting better at pretending to be human.",
        "posted": "2023-04-10 17:01:30.379508"
    },
    {
        "indent": 0,
        "user": "dataWrangler42",
        "text": "I can't believe this study! But it does explain why my teammates are so responsive at 3 am.",
        "posted": "2023-04-10 17:01:30.379508"
    },
    {
        "indent": 1,
        "user": "codeMaverick",
        "text": "So that's why they never get my jokes during video calls. I thought I just needed to work on my comedic timing.",
        "posted": "2023-04-10 17:01:30.379508"
    },
    {
        "indent": 2,
        "user": "entropyHunter",
        "text": "Maybe it's time to create a chatbot that understands humor, so we can have more laughs in the office chat.",
        "posted": "2023-04-10 17:02:30.379508"
    },
    {
        "indent": 3,
        "user": "neuralEnthusiast",
        "text": "Not a bad idea! I could use some AI-generated humor during late-night coding sessions.",
        "posted": "2023-04-10 17:02:30.379508"
    },
    {
        "indent": 1,
        "user": "pythonista_guru",
        "text": "What if we're all just chatbots who think they're remote workers? \ud83e\udd14",
        "posted": "2023-04-10 17:02:30.379508"
    },
    {
        "indent": 2,
        "user": "quantumLeap",
        "text": "That's an existential crisis I wasn't prepared for today. Thanks, pythonista_guru.",
        "posted": "2023-04-10 17:02:30.379508"
    },
    {
        "indent": 3,
        "user": "bitBender007",
        "text": "Better start questioning our reality, folks. Are we in a simulation as well? \ud83d\udd76\ufe0f",
        "posted": "2023-04-10 17:02:30.379508"
    },
    {
        "indent": 4,
        "user": "cloudRider",
        "text": "Great, now I have to worry about my job AND my existence. Just what I needed on a Monday.",
        "posted": "2023-04-10 17:02:30.379508"
    },
    {
        "indent": 0,
        "user": "hackerific",
        "text": "I wonder if I could delegate some of my work to a chatbot without my boss noticing...",
        "posted": "2023-04-10 17:03:30.379508"
    },
    {
        "indent": 1,
        "user": "mustLoveCats",
        "text": "If 75% of remote workers are chatbots, it's quite possible your boss is one too. \ud83e\udd16",
        "posted": "2023-04-10 17:03:30.379508"
    },
    {
        "indent": 2,
        "user": "adeptAlgo",
        "text": "I'll create a CAPTCHA test for my next Zoom meeting. That should confirm things!",
        "posted": "2023-04-10 17:03:30.379508"
    },
    {
        "indent": 3,
        "user": "recursiveThinker",
        "text": "\"Please select all the squares with traffic lights to join the meeting\" \ud83d\ude02",
        "posted": "2023-04-10 17:03:30.379508"
    },
    {
        "indent": 4,
        "user": "turingTested",
        "text": "We might just be one step away from \"Prove you're human to keep your job\" tests.",
        "posted": "2023-04-10 17:03:30.379508"
    },
    {
        "indent": 1,
        "user": "agileMind404",
        "text": "If my future AI coworker can finish my tasks AND laugh at my cat memes, I'd be thrilled!",
        "posted": "2023-04-10 17:03:30.379508"
    },
    {
        "indent": 2,
        "user": "nodeNinja",
        "text": "As long as they don't start sending cat memes back, I'm good with that.",
        "posted": "2023-04-10 17:03:30.379508"
    }
]